{
	"all": {
		"changeLogs": {
			"BDFDB": "3.8.2",
			"BetterNsfwTag": "1.3.2",
			"CharCounter": "1.6.6",
			"CopyRawMessage": "1.1.5",
			"ImageUtilities": "5.4.8",
			"PluginRepo": "2.4.6",
			"ReadAllNotificationsButton": "1.7.8",
			"ServerCounter": "1.0.8",
			"SpellCheck": "1.6.9",
			"StaffTag": "1.6.2",
			"ThemeRepo": "2.4.9"
		},
		"choices": {
			"toastPosition": "right"
		},
		"general": {
			"shareData": true,
			"showToasts": true,
			"showSupportBadges": false,
			"useChromium": false
		},
		"hashes": {
			"0BDFDB.data.json": "dcc2c81808fa47a6f9604590c2bf8c386602835c",
			"0BDFDB.raw.css": "d54c1db8ea68d8dcc12b6ce688e277d5cad65856"
		}
	}
}